dxcam/__init__.py
dxcam/dxcam.py
dxcam/_libs/__init__.py
dxcam/_libs/d3d11.py
dxcam/_libs/dxgi.py
dxcam/_libs/user32.py
dxcam/core/__init__.py
dxcam/core/device.py
dxcam/core/duplicator.py
dxcam/core/output.py
dxcam/core/stagesurf.py
dxcam/processor/__init__.py
dxcam/processor/base.py
dxcam/processor/numpy_processor.py
dxcam/util/__init__.py
dxcam/util/io.py
dxcam/util/timer.py
dxcam-0.0.5.dist-info/LICENSE
dxcam-0.0.5.dist-info/METADATA
dxcam-0.0.5.dist-info/WHEEL
dxcam-0.0.5.dist-info/top_level.txt
dxcam-0.0.5.dist-info/RECORD
